.coveragerc
.gitignore
.isort.cfg
.pre-commit-config.yaml
.travis.yml
AUTHORS.rst
CHANGELOG.rst
LICENSE.txt
Makefile
README.rst
requirements.txt
setup.cfg
setup.py
tox.ini
docs/Makefile
docs/authors.rst
docs/changelog.rst
docs/conf.py
docs/index.rst
docs/license.rst
docs/_static/.gitignore
src/publicdata/__init__.py
src/publicdata/pums/__init__.py
src/publicdata/pums/appurl.py
src/publicdata/pums/exceptions.py
src/publicdata/pums/meta.py
src/publicdata_pums.egg-info/PKG-INFO
src/publicdata_pums.egg-info/SOURCES.txt
src/publicdata_pums.egg-info/dependency_links.txt
src/publicdata_pums.egg-info/entry_points.txt
src/publicdata_pums.egg-info/not-zip-safe
src/publicdata_pums.egg-info/requires.txt
src/publicdata_pums.egg-info/top_level.txt
tests/conftest.py
tests/test_basic.py
tests/test_skeleton.py
tests/test_support.py
tests/travis_install.sh